cpanel_xss_2023/__init__.py
cpanel_xss_2023/main.py
cpanel_xss_2023/includes/__init__.py
cpanel_xss_2023/includes/bot.py
cpanel_xss_2023/includes/filereader.py
cpanel_xss_2023/includes/scan.py
cpanel_xss_2023/includes/writefile.py
cpanel_xss_2023/utils/__init__.py
cpanel_xss_2023/utils/configure.py
cpanel_xss_2023/utils/const.py
cpanel_xss_2023/utils/helpers.py
cpanel_xss_2023-1.1.dist-info/METADATA
cpanel_xss_2023-1.1.dist-info/WHEEL
cpanel_xss_2023-1.1.dist-info/entry_points.txt
cpanel_xss_2023-1.1.dist-info/top_level.txt
cpanel_xss_2023-1.1.dist-info/RECORD
