Metadata-Version: 2.1
Name: cpanel-xss-2023
Version: 1.1
Home-page: https://github.com/mdaseem03/cpanel_xss_2023
Requires-Dist: click
Requires-Dist: requests
Requires-Dist: PyYAML
